robotmpcs/__init__.py
robotmpcs/models/__init__.py
robotmpcs/models/diff_drive_mpc_model.py
robotmpcs/models/mpcModel.py
robotmpcs/planner/__init__.py
robotmpcs/planner/mpcPlanner.py
robotmpcs-0.2.1.dist-info/WHEEL
robotmpcs-0.2.1.dist-info/METADATA
robotmpcs-0.2.1.dist-info/RECORD
